kad/__init__.py
kad/bucketset.py
kad/hashing.py
kad/kad.py
kad/peer.py
kad/shortlist.py
kad/storage.py
kad.py-0.5.6.dist-info/DESCRIPTION.rst
kad.py-0.5.6.dist-info/METADATA
kad.py-0.5.6.dist-info/RECORD
kad.py-0.5.6.dist-info/WHEEL
kad.py-0.5.6.dist-info/metadata.json
kad.py-0.5.6.dist-info/top_level.txt
