Metadata-Version: 2.0
Name: kad.py
Version: 0.5.6
Summary: Python3 DHT Implementation
Home-page: https://github.com/dakk/kad.py
Author: Davide Gessa, Isaac Zafuta
Author-email: gessadavide@gmail.com, isaac@zafuta.com
License: Copyright (c) 2015, Davide Gessa
